smart_automation/__init__.py
smart_automation/client.cp313-win_amd64.pyd
smart_automation-0.2.2.dist-info/METADATA
smart_automation-0.2.2.dist-info/WHEEL
smart_automation-0.2.2.dist-info/top_level.txt
smart_automation-0.2.2.dist-info/RECORD
