Metadata-Version: 2.4
Name: smart_automation
Version: 0.2.2
Summary: Smart GUI Automation Library for Windows Forms (Binary Distribution)
Author: User
Requires-Python: >=3.7
Requires-Dist: pywinauto
Requires-Dist: requests
